{
  "mode": "pre",
  "tag": "alpha",
  "initialVersions": {
    "@lit-protocol/access-control-conditions": "8.0.0-alpha.0",
    "@lit-protocol/access-control-conditions-schemas": "8.0.0-alpha.0",
    "@lit-protocol/auth": "8.0.0-alpha.0",
    "@lit-protocol/auth-helpers": "8.0.0-alpha.0",
    "@lit-protocol/constants": "8.0.0-alpha.0",
    "@lit-protocol/crypto": "8.0.0-alpha.0",
    "@lit-protocol/lit-client": "8.0.0-alpha.0",
    "@lit-protocol/logger": "8.0.0-alpha.0",
    "@lit-protocol/networks": "8.0.0-alpha.0",
    "@lit-protocol/schemas": "8.0.0-alpha.0",
    "@lit-protocol/types": "8.0.0-alpha.0",
    "@lit-protocol/wasm": "8.0.0-alpha.0",
    "@lit-protocol/wrapped-keys": "8.0.0-alpha.0",
    "@lit-protocol/wrapped-keys-lit-actions": "8.0.0-alpha.0"
  },
  "changesets": [
    "hot-baboons-help",
    "yellow-seas-crash"
  ]
}
